<?xml version="1.0" encoding="utf-8" ?>
<tree-map>
  <no-comparator/>
  <entry>
    <int>1</int>
    <fire.pb.mission.SActivityQuestion>
      <id>1</id>
      <questionid>1</questionid>
      <step>0</step>
      <question>难度最低的任务是什么？</question>
      <answer1>傲来封妖</answer1>
      <answer2>皇宫飞贼</answer2>
      <answer3>飞升副本</answer3>
      <rightanswer>1</rightanswer>
      <rightrewardid>5840</rightrewardid>
      <errorrewardid>5850</errorrewardid>
    </fire.pb.mission.SActivityQuestion>
  </entry>
  <entry>
    <int>2</int>
    <fire.pb.mission.SActivityQuestion>
      <id>2</id>
      <questionid>2</questionid>
      <step>0</step>
      <question>所有BOSS中难度最高的任务是什么？</question>
      <answer1>生死劫</answer1>
      <answer2>蚩尤封印</answer2>
      <answer3>6星天罡地煞</answer3>
      <rightanswer>2</rightanswer>
      <rightrewardid>5840</rightrewardid>
      <errorrewardid>5850</errorrewardid>
    </fire.pb.mission.SActivityQuestion>
  </entry>
  <entry>
    <int>3</int>
    <fire.pb.mission.SActivityQuestion>
      <id>3</id>
      <questionid>3</questionid>
      <step>0</step>
      <question>提升修炼最快的方法是什么？</question>
      <answer1>跑环</answer1>
      <answer2>刷BOSS</answer2>
      <answer3>找GM</answer3>
      <rightanswer>1</rightanswer>
      <rightrewardid>5840</rightrewardid>
      <errorrewardid>5850</errorrewardid>
    </fire.pb.mission.SActivityQuestion>
  </entry>
  <entry>
    <int>4</int>
    <fire.pb.mission.SActivityQuestion>
      <id>4</id>
      <questionid>4</questionid>
      <step>0</step>
      <question>修炼最高多少级？</question>
      <answer1>40</answer1>
      <answer2>30</answer2>
      <answer3>20</answer3>
      <rightanswer>1</rightanswer>
      <rightrewardid>5840</rightrewardid>
      <errorrewardid>5850</errorrewardid>
    </fire.pb.mission.SActivityQuestion>
  </entry>
  <entry>
    <int>5</int>
    <fire.pb.mission.SActivityQuestion>
      <id>5</id>
      <questionid>5</questionid>
      <step>0</step>
      <question>高级宝图打什么可以掉落？</question>
      <answer1>店小二任务</answer1>
      <answer2>所有BOSS</answer2>
      <answer3>星宿</answer3>
      <rightanswer>2</rightanswer>
      <rightrewardid>5840</rightrewardid>
      <errorrewardid>5850</errorrewardid>
    </fire.pb.mission.SActivityQuestion>
  </entry>
  <entry>
    <int>6</int>
    <fire.pb.mission.SActivityQuestion>
      <id>6</id>
      <questionid>6</questionid>
      <step>0</step>
      <question>每天必做的任务是什么？</question>
      <answer1>师门</answer1>
      <answer2>答题</answer2>
      <answer3>以上皆是</answer3>
      <rightanswer>3</rightanswer>
      <rightrewardid>5840</rightrewardid>
      <errorrewardid>5850</errorrewardid>
    </fire.pb.mission.SActivityQuestion>
  </entry>
  <entry>
    <int>7</int>
    <fire.pb.mission.SActivityQuestion>
      <id>7</id>
      <questionid>7</questionid>
      <step>0</step>
      <question>月卡多少仙玉一张？</question>
      <answer1>9800个</answer1>
      <answer2>300个</answer2>
      <answer3>9800万</answer3>
      <rightanswer>3</rightanswer>
      <rightrewardid>5840</rightrewardid>
      <errorrewardid>5850</errorrewardid>
    </fire.pb.mission.SActivityQuestion>
  </entry>
  <entry>
    <int>8</int>
    <fire.pb.mission.SActivityQuestion>
      <id>8</id>
      <questionid>8</questionid>
      <step>0</step>
      <question>GM首充多少钱？</question>
      <answer1>不充值</answer1>
      <answer2>没有首充</answer2>
      <answer3>10元</answer3>
      <rightanswer>2</rightanswer>
      <rightrewardid>5840</rightrewardid>
      <errorrewardid>5850</errorrewardid>
    </fire.pb.mission.SActivityQuestion>
  </entry>
  <entry>
    <int>9</int>
    <fire.pb.mission.SActivityQuestion>
      <id>9</id>
      <questionid>9</questionid>
      <step>0</step>
      <question>摆摊交易需要什么？</question>
      <answer1>什么都不需要</answer1>
      <answer2>信用值</answer2>
      <answer3>金币</answer3>
      <rightanswer>2</rightanswer>
      <rightrewardid>5840</rightrewardid>
      <errorrewardid>5850</errorrewardid>
    </fire.pb.mission.SActivityQuestion>
  </entry>
  <entry>
    <int>10</int>
    <fire.pb.mission.SActivityQuestion>
      <id>10</id>
      <questionid>10</questionid>
      <step>0</step>
      <question>需要激活什么才能摆摊交易？</question>
      <answer1>免费关联手机</answer1>
      <answer2>课金</answer2>
      <answer3>找GM</answer3>
      <rightanswer>1</rightanswer>
      <rightrewardid>5840</rightrewardid>
      <errorrewardid>5850</errorrewardid>
    </fire.pb.mission.SActivityQuestion>
  </entry>
  <entry>
    <int>11</int>
    <fire.pb.mission.SActivityQuestion>
      <id>11</id>
      <questionid>11</questionid>
      <step>0</step>
      <question>本服共有多少个门派？</question>
      <answer1>15</answer1>
      <answer2>10</answer2>
      <answer3>12</answer3>
      <rightanswer>1</rightanswer>
      <rightrewardid>5840</rightrewardid>
      <errorrewardid>5850</errorrewardid>
    </fire.pb.mission.SActivityQuestion>
  </entry>
  <entry>
    <int>12</int>
    <fire.pb.mission.SActivityQuestion>
      <id>12</id>
      <questionid>12</questionid>
      <step>0</step>
      <question>门派大唐官府主要作用是什么？</question>
      <answer1>点杀</answer1>
      <answer2>加血</answer2>
      <answer3>封印</answer3>
      <rightanswer>1</rightanswer>
      <rightrewardid>5840</rightrewardid>
      <errorrewardid>5850</errorrewardid>
    </fire.pb.mission.SActivityQuestion>
  </entry>
  <entry>
    <int>13</int>
    <fire.pb.mission.SActivityQuestion>
      <id>13</id>
      <questionid>13</questionid>
      <step>0</step>
      <question>门派化生寺主要作用是什么？</question>
      <answer1>隐身</answer1>
      <answer2>点杀</answer2>
      <answer3>加血</answer3>
      <rightanswer>3</rightanswer>
      <rightrewardid>5840</rightrewardid>
      <errorrewardid>5850</errorrewardid>
    </fire.pb.mission.SActivityQuestion>
  </entry>
  <entry>
    <int>14</int>
    <fire.pb.mission.SActivityQuestion>
      <id>14</id>
      <questionid>14</questionid>
      <step>0</step>
      <question>门派方寸山主要作用是什么？</question>
      <answer1>救人</answer1>
      <answer2>群秒</answer2>
      <answer3>封印</answer3>
      <rightanswer>3</rightanswer>
      <rightrewardid>5840</rightrewardid>
      <errorrewardid>5850</errorrewardid>
    </fire.pb.mission.SActivityQuestion>
  </entry>
  <entry>
    <int>15</int>
    <fire.pb.mission.SActivityQuestion>
      <id>15</id>
      <questionid>15</questionid>
      <step>0</step>
      <question>门派狮驼岭主要作用是什么？</question>
      <answer1>群攻</answer1>
      <answer2>群秒</answer2>
      <answer3>点杀</answer3>
      <rightanswer>1</rightanswer>
      <rightrewardid>5840</rightrewardid>
      <errorrewardid>5850</errorrewardid>
    </fire.pb.mission.SActivityQuestion>
  </entry>
  <entry>
    <int>16</int>
    <fire.pb.mission.SActivityQuestion>
      <id>16</id>
      <questionid>16</questionid>
      <step>0</step>
      <question>门派魔王寨主要作用是什么？</question>
      <answer1>群秒</answer1>
      <answer2>加血</answer2>
      <answer3>辅助</answer3>
      <rightanswer>1</rightanswer>
      <rightrewardid>5840</rightrewardid>
      <errorrewardid>5850</errorrewardid>
    </fire.pb.mission.SActivityQuestion>
  </entry>
  <entry>
    <int>17</int>
    <fire.pb.mission.SActivityQuestion>
      <id>17</id>
      <questionid>17</questionid>
      <step>0</step>
      <question>门派阴府主要作用是什么？</question>
      <answer1>隐身</answer1>
      <answer2>加血</answer2>
      <answer3>封印</answer3>
      <rightanswer>2</rightanswer>
      <rightrewardid>5840</rightrewardid>
      <errorrewardid>5850</errorrewardid>
    </fire.pb.mission.SActivityQuestion>
  </entry>
  <entry>
    <int>18</int>
    <fire.pb.mission.SActivityQuestion>
      <id>18</id>
      <questionid>18</questionid>
      <step>0</step>
      <question>门派盘丝洞主要作用是什么？</question>
      <answer1>点杀</answer1>
      <answer2>群攻</answer2>
      <answer3>封印</answer3>
      <rightanswer>3</rightanswer>
      <rightrewardid>5840</rightrewardid>
      <errorrewardid>5850</errorrewardid>
    </fire.pb.mission.SActivityQuestion>
  </entry>
  <entry>
    <int>19</int>
    <fire.pb.mission.SActivityQuestion>
      <id>19</id>
      <questionid>19</questionid>
      <step>0</step>
      <question>门派凌波城要作用是什么？</question>
      <answer1>封印</answer1>
      <answer2>群攻</answer2>
      <answer3>群秒</answer3>
      <rightanswer>2</rightanswer>
      <rightrewardid>5840</rightrewardid>
      <errorrewardid>5850</errorrewardid>
    </fire.pb.mission.SActivityQuestion>
  </entry>
  <entry>
    <int>20</int>
    <fire.pb.mission.SActivityQuestion>
      <id>20</id>
      <questionid>20</questionid>
      <step>0</step>
      <question>门派五庄观主要作用是什么？</question>
      <answer1>封印</answer1>
      <answer2>群攻</answer2>
      <answer3>群秒</answer3>
      <rightanswer>1</rightanswer>
      <rightrewardid>5840</rightrewardid>
      <errorrewardid>5850</errorrewardid>
    </fire.pb.mission.SActivityQuestion>
  </entry>
  <entry>
    <int>21</int>
    <fire.pb.mission.SActivityQuestion>
      <id>21</id>
      <questionid>21</questionid>
      <step>0</step>
      <question>袁守城在那个位置？</question>
      <answer1>建业</answer1>
      <answer2>西梁女国</answer2>
      <answer3>长安</answer3>
      <rightanswer>3</rightanswer>
      <rightrewardid>5840</rightrewardid>
      <errorrewardid>5850</errorrewardid>
    </fire.pb.mission.SActivityQuestion>
  </entry>
  <entry>
    <int>22</int>
    <fire.pb.mission.SActivityQuestion>
      <id>22</id>
      <questionid>22</questionid>
      <step>0</step>
      <question>商城宝石最高可以购买多少级？</question>
      <answer1>10</answer1>
      <answer2>8</answer2>
      <answer3>9</answer3>
      <rightanswer>1</rightanswer>
      <rightrewardid>5840</rightrewardid>
      <errorrewardid>5850</errorrewardid>
    </fire.pb.mission.SActivityQuestion>
  </entry>
  <entry>
    <int>23</int>
    <fire.pb.mission.SActivityQuestion>
      <id>23</id>
      <questionid>23</questionid>
      <step>0</step>
      <question>等级突破找谁？</question>
      <answer1>泡泡</answer1>
      <answer2>GM</answer2>
      <answer3>袁守城</answer3>
      <rightanswer>2</rightanswer>
      <rightrewardid>5840</rightrewardid>
      <errorrewardid>5850</errorrewardid>
    </fire.pb.mission.SActivityQuestion>
  </entry>
  <entry>
    <int>24</int>
    <fire.pb.mission.SActivityQuestion>
      <id>24</id>
      <questionid>24</questionid>
      <step>0</step>
      <question>神兽总共可以突破多少次？</question>
      <answer1>3</answer1>
      <answer2>2</answer2>
      <answer3>1</answer3>
      <rightanswer>3</rightanswer>
      <rightrewardid>5840</rightrewardid>
      <errorrewardid>5850</errorrewardid>
    </fire.pb.mission.SActivityQuestion>
  </entry>
  <entry>
    <int>25</int>
    <fire.pb.mission.SActivityQuestion>
      <id>25</id>
      <questionid>25</questionid>
      <step>0</step>
      <question>本服是什么服？</question>
      <answer1>极致仿官</answer1>
      <answer2>微变态</answer2>
      <answer3>超变态</answer3>
      <rightanswer>1</rightanswer>
      <rightrewardid>5840</rightrewardid>
      <errorrewardid>5850</errorrewardid>
    </fire.pb.mission.SActivityQuestion>
  </entry>
  <entry>
    <int>26</int>
    <fire.pb.mission.SActivityQuestion>
      <id>26</id>
      <questionid>26</questionid>
      <step>0</step>
      <question>鬼将是多少等级擕带的宝宝？</question>
      <answer1>95</answer1>
      <answer2>100</answer2>
      <answer3>105</answer3>
      <rightanswer>3</rightanswer>
      <rightrewardid>5840</rightrewardid>
      <errorrewardid>5850</errorrewardid>
    </fire.pb.mission.SActivityQuestion>
  </entry>
  <entry>
    <int>27</int>
    <fire.pb.mission.SActivityQuestion>
      <id>27</id>
      <questionid>27</questionid>
      <step>0</step>
      <question>大力金刚是多少等级擕带的宝宝？</question>
      <answer1>135</answer1>
      <answer2>125</answer2>
      <answer3>105</answer3>
      <rightanswer>2</rightanswer>
      <rightrewardid>5840</rightrewardid>
      <errorrewardid>5850</errorrewardid>
    </fire.pb.mission.SActivityQuestion>
  </entry>
  <entry>
    <int>28</int>
    <fire.pb.mission.SActivityQuestion>
      <id>28</id>
      <questionid>28</questionid>
      <step>0</step>
      <question>护卫是多少等级擕带的宝宝？</question>
      <answer1>5</answer1>
      <answer2>1</answer2>
      <answer3>0</answer3>
      <rightanswer>1</rightanswer>
      <rightrewardid>5840</rightrewardid>
      <errorrewardid>5850</errorrewardid>
    </fire.pb.mission.SActivityQuestion>
  </entry>
  <entry>
    <int>29</int>
    <fire.pb.mission.SActivityQuestion>
      <id>29</id>
      <questionid>29</questionid>
      <step>0</step>
      <question>修罗傀儡鬼是多少等级擕带的宝宝？</question>
      <answer1>115</answer1>
      <answer2>125</answer2>
      <answer3>135</answer3>
      <rightanswer>3</rightanswer>
      <rightrewardid>5840</rightrewardid>
      <errorrewardid>5850</errorrewardid>
    </fire.pb.mission.SActivityQuestion>
  </entry>
  <entry>
    <int>30</int>
    <fire.pb.mission.SActivityQuestion>
      <id>30</id>
      <questionid>30</questionid>
      <step>0</step>
      <question>修罗傀儡妖是多少等级擕带的宝宝？</question>
      <answer1>135</answer1>
      <answer2>145</answer2>
      <answer3>125</answer3>
      <rightanswer>2</rightanswer>
      <rightrewardid>5840</rightrewardid>
      <errorrewardid>5850</errorrewardid>
    </fire.pb.mission.SActivityQuestion>
  </entry>
  <entry>
    <int>31</int>
    <fire.pb.mission.SActivityQuestion>
      <id>31</id>
      <questionid>31</questionid>
      <step>0</step>
      <question>蜃气妖是多少等级擕带的宝宝？</question>
      <answer1>155</answer1>
      <answer2>145</answer2>
      <answer3>135</answer3>
      <rightanswer>1</rightanswer>
      <rightrewardid>5840</rightrewardid>
      <errorrewardid>5850</errorrewardid>
    </fire.pb.mission.SActivityQuestion>
  </entry>
  <entry>
    <int>32</int>
    <fire.pb.mission.SActivityQuestion>
      <id>32</id>
      <questionid>32</questionid>
      <step>0</step>
      <question>凈瓶女娲是多少等级擕带的宝宝？</question>
      <answer1>115</answer1>
      <answer2>105</answer2>
      <answer3>95</answer3>
      <rightanswer>2</rightanswer>
      <rightrewardid>5840</rightrewardid>
      <errorrewardid>5850</errorrewardid>
    </fire.pb.mission.SActivityQuestion>
  </entry>
  <entry>
    <int>33</int>
    <fire.pb.mission.SActivityQuestion>
      <id>33</id>
      <questionid>33</questionid>
      <step>0</step>
      <question>毗舍童子是多少等级擕带的宝宝？</question>
      <answer1>135</answer1>
      <answer2>145</answer2>
      <answer3>155</answer3>
      <rightanswer>3</rightanswer>
      <rightrewardid>5840</rightrewardid>
      <errorrewardid>5850</errorrewardid>
    </fire.pb.mission.SActivityQuestion>
  </entry>
  <entry>
    <int>34</int>
    <fire.pb.mission.SActivityQuestion>
      <id>34</id>
      <questionid>34</questionid>
      <step>0</step>
      <question>幽灵是多少等级擕带的宝宝？</question>
      <answer1>95</answer1>
      <answer2>105</answer2>
      <answer3>100</answer3>
      <rightanswer>1</rightanswer>
      <rightrewardid>5840</rightrewardid>
      <errorrewardid>5850</errorrewardid>
    </fire.pb.mission.SActivityQuestion>
  </entry>
  <entry>
    <int>35</int>
    <fire.pb.mission.SActivityQuestion>
      <id>35</id>
      <questionid>35</questionid>
      <step>0</step>
      <question>游戏发现有人拉人、打广告应该？</question>
      <answer1>向GM举报</answer1>
      <answer2>一起拉</answer2>
      <answer3>当作看不见</answer3>
      <rightanswer>1</rightanswer>
      <rightrewardid>5840</rightrewardid>
      <errorrewardid>5850</errorrewardid>
    </fire.pb.mission.SActivityQuestion>
  </entry>
  <entry>
    <int>36</int>
    <fire.pb.mission.SActivityQuestion>
      <id>36</id>
      <questionid>36</questionid>
      <step>0</step>
      <question>律法女娲是多少等级擕带的宝宝？</question>
      <answer1>95</answer1>
      <answer2>105</answer2>
      <answer3>100</answer3>
      <rightanswer>1</rightanswer>
      <rightrewardid>5840</rightrewardid>
      <errorrewardid>5850</errorrewardid>
    </fire.pb.mission.SActivityQuestion>
  </entry>
  <entry>
    <int>37</int>
    <fire.pb.mission.SActivityQuestion>
      <id>37</id>
      <questionid>37</questionid>
      <step>0</step>
      <question>举报游戏拉人、打广告奖励多少金币？</question>
      <answer1>5万</answer1>
      <answer2>10万</answer2>
      <answer3>30万</answer3>
      <rightanswer>3</rightanswer>
      <rightrewardid>5840</rightrewardid>
      <errorrewardid>5850</errorrewardid>
    </fire.pb.mission.SActivityQuestion>
  </entry>
  <entry>
    <int>38</int>
    <fire.pb.mission.SActivityQuestion>
      <id>38</id>
      <questionid>38</questionid>
      <step>0</step>
      <question>群內发现有人拉人、打广告应该？</question>
      <answer1>向GM举报</answer1>
      <answer2>一起拉</answer2>
      <answer3>当作看不见</answer3>
      <rightanswer>1</rightanswer>
      <rightrewardid>5840</rightrewardid>
      <errorrewardid>5850</errorrewardid>
    </fire.pb.mission.SActivityQuestion>
  </entry>
  <entry>
    <int>39</int>
    <fire.pb.mission.SActivityQuestion>
      <id>39</id>
      <questionid>39</questionid>
      <step>0</step>
      <question>举报群內拉人奖励多少金币？</question>
      <answer1>10万</answer1>
      <answer2>30万</answer2>
      <answer3>5万</answer3>
      <rightanswer>2</rightanswer>
      <rightrewardid>5840</rightrewardid>
      <errorrewardid>5850</errorrewardid>
    </fire.pb.mission.SActivityQuestion>
  </entry>
  <entry>
    <int>40</int>
    <fire.pb.mission.SActivityQuestion>
      <id>40</id>
      <questionid>40</questionid>
      <step>0</step>
      <question>三界菁英是什么活动第一的称谓？</question>
      <answer1>帮派竞赛</answer1>
      <answer2>比武大会</answer2>
      <answer3>门派闯关</answer3>
      <rightanswer>3</rightanswer>
      <rightrewardid>5840</rightrewardid>
      <errorrewardid>5850</errorrewardid>
    </fire.pb.mission.SActivityQuestion>
  </entry>
  <entry>
    <int>41</int>
    <fire.pb.mission.SActivityQuestion>
      <id>41</id>
      <questionid>41</questionid>
      <step>0</step>
      <question>本服装备最高多少级？</question>
      <answer1>155</answer1>
      <answer2>150</answer2>
      <answer3>160</answer3>
      <rightanswer>2</rightanswer>
      <rightrewardid>5840</rightrewardid>
      <errorrewardid>5850</errorrewardid>
    </fire.pb.mission.SActivityQuestion>
  </entry>
  <entry>
    <int>42</int>
    <fire.pb.mission.SActivityQuestion>
      <id>42</id>
      <questionid>42</questionid>
      <step>0</step>
      <question>本服宝石最高可以合多少级？</question>
      <answer1>21</answer1>
      <answer2>15</answer2>
      <answer3>16</answer3>
      <rightanswer>1</rightanswer>
      <rightrewardid>5840</rightrewardid>
      <errorrewardid>5850</errorrewardid>
    </fire.pb.mission.SActivityQuestion>
  </entry>
  <entry>
    <int>43</int>
    <fire.pb.mission.SActivityQuestion>
      <id>43</id>
      <questionid>43</questionid>
      <step>0</step>
      <question>多少级装备可以镶嵌21级宝石？</question>
      <answer1>160</answer1>
      <answer2>210</answer2>
      <answer3>150</answer3>
      <rightanswer>3</rightanswer>
      <rightrewardid>5840</rightrewardid>
      <errorrewardid>5850</errorrewardid>
    </fire.pb.mission.SActivityQuestion>
  </entry>
  <entry>
    <int>44</int>
    <fire.pb.mission.SActivityQuestion>
      <id>44</id>
      <questionid>44</questionid>
      <step>0</step>
      <question>什么特效可以穿比自身更高级的装备？</question>
      <answer1>神农</answer1>
      <answer2>无视装备等级</answer2>
      <answer3>无级别限制</answer3>
      <rightanswer>3</rightanswer>
      <rightrewardid>5840</rightrewardid>
      <errorrewardid>5850</errorrewardid>
    </fire.pb.mission.SActivityQuestion>
  </entry>
  <entry>
    <int>45</int>
    <fire.pb.mission.SActivityQuestion>
      <id>45</id>
      <questionid>45</questionid>
      <step>0</step>
      <question>一件装备最高可以镶嵌多少个宝石？</question>
      <answer1>3</answer1>
      <answer2>2</answer2>
      <answer3>5</answer3>
      <rightanswer>1</rightanswer>
      <rightrewardid>5840</rightrewardid>
      <errorrewardid>5850</errorrewardid>
    </fire.pb.mission.SActivityQuestion>
  </entry>
  <entry>
    <int>46</int>
    <fire.pb.mission.SActivityQuestion>
      <id>46</id>
      <questionid>46</questionid>
      <step>0</step>
      <question>本服灵饰最高多少级？</question>
      <answer1>120</answer1>
      <answer2>140</answer2>
      <answer3>160</answer3>
      <rightanswer>2</rightanswer>
      <rightrewardid>5840</rightrewardid>
      <errorrewardid>5850</errorrewardid>
    </fire.pb.mission.SActivityQuestion>
  </entry>
  <entry>
    <int>47</int>
    <fire.pb.mission.SActivityQuestion>
      <id>47</id>
      <questionid>47</questionid>
      <step>0</step>
      <question>月卡一天可以免费得多少金币？</question>
      <answer1>5万</answer1>
      <answer2>10万</answer2>
      <answer3>50万</answer3>
      <rightanswer>3</rightanswer>
      <rightrewardid>5840</rightrewardid>
      <errorrewardid>5850</errorrewardid>
    </fire.pb.mission.SActivityQuestion>
  </entry>
  <entry>
    <int>48</int>
    <fire.pb.mission.SActivityQuestion>
      <id>48</id>
      <questionid>48</questionid>
      <step>0</step>
      <question>月卡一天可以免费得多少信用值？</question>
      <answer1>10万</answer1>
      <answer2>5万</answer2>
      <answer3>3万</answer3>
      <rightanswer>1</rightanswer>
      <rightrewardid>5840</rightrewardid>
      <errorrewardid>5850</errorrewardid>
    </fire.pb.mission.SActivityQuestion>
  </entry>
  <entry>
    <int>49</int>
    <fire.pb.mission.SActivityQuestion>
      <id>49</id>
      <questionid>49</questionid>
      <step>0</step>
      <question>月卡一天可以免费得多少神兜兜？</question>
      <answer1>5个</answer1>
      <answer2>10个</answer2>
      <answer3>20个</answer3>
      <rightanswer>2</rightanswer>
      <rightrewardid>5840</rightrewardid>
      <errorrewardid>5850</errorrewardid>
    </fire.pb.mission.SActivityQuestion>
  </entry>
  <entry>
    <int>50</int>
    <fire.pb.mission.SActivityQuestion>
      <id>50</id>
      <questionid>50</questionid>
      <step>0</step>
      <question>月卡一天可以免费得多少修炼果和九转金丹？</question>
      <answer1>1千个</answer1>
      <answer2>2千个</answer2>
      <answer3>3千个</answer3>
      <rightanswer>2</rightanswer>
      <rightrewardid>5840</rightrewardid>
      <errorrewardid>5850</errorrewardid>
    </fire.pb.mission.SActivityQuestion>
  </entry>
  <entry>
    <int>51</int>
    <fire.pb.mission.SActivityQuestion>
      <id>51</id>
      <questionid>51</questionid>
      <step>0</step>
      <question>月卡多少钱一张？</question>
      <answer1>30元</answer1>
      <answer2>40元</answer2>
      <answer3>50元</answer3>
      <rightanswer>1</rightanswer>
      <rightrewardid>5840</rightrewardid>
      <errorrewardid>5850</errorrewardid>
    </fire.pb.mission.SActivityQuestion>
  </entry>
  <entry>
    <int>52</int>
    <fire.pb.mission.SActivityQuestion>
      <id>52</id>
      <questionid>52</questionid>
      <step>0</step>
      <question>GM开服的原因？</question>
      <answer1>赚钱</answer1>
      <answer2>热爱梦幻</answer2>
      <answer3>无聊</answer3>
      <rightanswer>2</rightanswer>
      <rightrewardid>5840</rightrewardid>
      <errorrewardid>5850</errorrewardid>
    </fire.pb.mission.SActivityQuestion>
  </entry>
  <entry>
    <int>53</int>
    <fire.pb.mission.SActivityQuestion>
      <id>53</id>
      <questionid>53</questionid>
      <step>0</step>
      <question>星宿的奖励多少金币？</question>
      <answer1>5555</answer1>
      <answer2>6666</answer2>
      <answer3>7777</answer3>
      <rightanswer>1</rightanswer>
      <rightrewardid>5840</rightrewardid>
      <errorrewardid>5850</errorrewardid>
    </fire.pb.mission.SActivityQuestion>
  </entry>
  <entry>
    <int>54</int>
    <fire.pb.mission.SActivityQuestion>
      <id>54</id>
      <questionid>54</questionid>
      <step>0</step>
      <question>梦魔夜叉奖励多少金币？</question>
      <answer1>15555</answer1>
      <answer2>13333</answer2>
      <answer3>11111</answer3>
      <rightanswer>3</rightanswer>
      <rightrewardid>5840</rightrewardid>
      <errorrewardid>5850</errorrewardid>
    </fire.pb.mission.SActivityQuestion>
  </entry>
  <entry>
    <int>55</int>
    <fire.pb.mission.SActivityQuestion>
      <id>55</id>
      <questionid>55</questionid>
      <step>0</step>
      <question>星宿多少超过多少钱不能打？</question>
      <answer1>109</answer1>
      <answer2>100</answer2>
      <answer3>105</answer3>
      <rightanswer>1</rightanswer>
      <rightrewardid>5840</rightrewardid>
      <errorrewardid>5850</errorrewardid>
    </fire.pb.mission.SActivityQuestion>
  </entry>
  <entry>
    <int>56</int>
    <fire.pb.mission.SActivityQuestion>
      <id>56</id>
      <questionid>56</questionid>
      <step>0</step>
      <question>梦魔夜叉要多少级才可以打？</question>
      <answer1>100</answer1>
      <answer2>105</answer2>
      <answer3>109</answer3>
      <rightanswer>1</rightanswer>
      <rightrewardid>5840</rightrewardid>
      <errorrewardid>5850</errorrewardid>
    </fire.pb.mission.SActivityQuestion>
  </entry>
  <entry>
    <int>57</int>
    <fire.pb.mission.SActivityQuestion>
      <id>57</id>
      <questionid>57</questionid>
      <step>0</step>
      <question>宝宝最高可以合成多少技能？</question>
      <answer1>17</answer1>
      <answer2>15</answer2>
      <answer3>16</answer3>
      <rightanswer>3</rightanswer>
      <rightrewardid>5840</rightrewardid>
      <errorrewardid>5850</errorrewardid>
    </fire.pb.mission.SActivityQuestion>
  </entry>
  <entry>
    <int>58</int>
    <fire.pb.mission.SActivityQuestion>
      <id>58</id>
      <questionid>58</questionid>
      <step>0</step>
      <question>一只宝宝最多可以吃多少个元宵？</question>
      <answer1>15个</answer1>
      <answer2>10个</answer2>
      <answer3>20个</answer3>
      <rightanswer>2</rightanswer>
      <rightrewardid>5840</rightrewardid>
      <errorrewardid>5850</errorrewardid>
    </fire.pb.mission.SActivityQuestion>
  </entry>
  <entry>
    <int>59</int>
    <fire.pb.mission.SActivityQuestion>
      <id>59</id>
      <questionid>59</questionid>
      <step>0</step>
      <question>以下其中那个是稀有技能？</question>
      <answer1>高级必杀</answer1>
      <answer2>洞察</answer2>
      <answer3>水漫金山</answer3>
      <rightanswer>2</rightanswer>
      <rightrewardid>5840</rightrewardid>
      <errorrewardid>5850</errorrewardid>
    </fire.pb.mission.SActivityQuestion>
  </entry>
  <entry>
    <int>60</int>
    <fire.pb.mission.SActivityQuestion>
      <id>60</id>
      <questionid>60</questionid>
      <step>0</step>
      <question>以下其中那个是稀有技能？</question>
      <answer1>力劈华山</answer1>
      <answer2>高级连击</answer2>
      <answer3>高级偷袭</answer3>
      <rightanswer>1</rightanswer>
      <rightrewardid>5840</rightrewardid>
      <errorrewardid>5850</errorrewardid>
    </fire.pb.mission.SActivityQuestion>
  </entry>
  <entry>
    <int>61</int>
    <fire.pb.mission.SActivityQuestion>
      <id>61</id>
      <questionid>61</questionid>
      <step>0</step>
      <question>以下其中那个是稀有技能？</question>
      <answer1>神马浮云</answer1>
      <answer2>高级强力</answer2>
      <answer3>高级夜战</answer3>
      <rightanswer>1</rightanswer>
      <rightrewardid>5840</rightrewardid>
      <errorrewardid>5850</errorrewardid>
    </fire.pb.mission.SActivityQuestion>
  </entry>
  <entry>
    <int>62</int>
    <fire.pb.mission.SActivityQuestion>
      <id>62</id>
      <questionid>62</questionid>
      <step>0</step>
      <question>以下其中那个是稀有技能？</question>
      <answer1>高级法爆</answer1>
      <answer2>须弥真言</answer2>
      <answer3>级级魔之心</answer3>
      <rightanswer>2</rightanswer>
      <rightrewardid>5840</rightrewardid>
      <errorrewardid>5850</errorrewardid>
    </fire.pb.mission.SActivityQuestion>
  </entry>
  <entry>
    <int>63</int>
    <fire.pb.mission.SActivityQuestion>
      <id>63</id>
      <questionid>63</questionid>
      <step>0</step>
      <question>以下其中那个是稀有技能？</question>
      <answer1>高级否定</answer1>
      <answer2>高级水吸</answer2>
      <answer3>劫雷降临</answer3>
      <rightanswer>3</rightanswer>
      <rightrewardid>5840</rightrewardid>
      <errorrewardid>5850</errorrewardid>
    </fire.pb.mission.SActivityQuestion>
  </entry>
  <entry>
    <int>64</int>
    <fire.pb.mission.SActivityQuestion>
      <id>64</id>
      <questionid>64</questionid>
      <step>0</step>
      <question>以下那个BOSS难度最大？</question>
      <answer1>皇宫飞贼</answer1>
      <answer2>万年妖王</answer2>
      <answer3>大唐官职</answer3>
      <rightanswer>2</rightanswer>
      <rightrewardid>5840</rightrewardid>
      <errorrewardid>5850</errorrewardid>
    </fire.pb.mission.SActivityQuestion>
  </entry>
  <entry>
    <int>65</int>
    <fire.pb.mission.SActivityQuestion>
      <id>65</id>
      <questionid>65</questionid>
      <step>0</step>
      <question>以下那个BOSS难度最大？</question>
      <answer1>傲来封妖</answer1>
      <answer2>大唐官职</answer2>
      <answer3>皇宫飞贼</answer3>
      <rightanswer>3</rightanswer>
      <rightrewardid>5840</rightrewardid>
      <errorrewardid>5850</errorrewardid>
    </fire.pb.mission.SActivityQuestion>
  </entry>
  <entry>
    <int>66</int>
    <fire.pb.mission.SActivityQuestion>
      <id>66</id>
      <questionid>66</questionid>
      <step>0</step>
      <question>以下那个BOSS难度最大？</question>
      <answer1>蚩尤封印</answer1>
      <answer2>6星天罡</answer2>
      <answer3>6星地煞</answer3>
      <rightanswer>1</rightanswer>
      <rightrewardid>5840</rightrewardid>
      <errorrewardid>5850</errorrewardid>
    </fire.pb.mission.SActivityQuestion>
  </entry>
  <entry>
    <int>67</int>
    <fire.pb.mission.SActivityQuestion>
      <id>67</id>
      <questionid>67</questionid>
      <step>0</step>
      <question>以下那个门派能给队友加奶?</question>
      <answer1>化生寺</answer1>
      <answer2>大唐官职</answer2>
      <answer3>方寸山</answer3>
      <rightanswer>1</rightanswer>
      <rightrewardid>5840</rightrewardid>
      <errorrewardid>5850</errorrewardid>
    </fire.pb.mission.SActivityQuestion>
  </entry>
  <entry>
    <int>68</int>
    <fire.pb.mission.SActivityQuestion>
      <id>68</id>
      <questionid>68</questionid>
      <step>0</step>
      <question>以下那个门派能给队友加奶?</question>
      <answer1>五庄观</answer1>
      <answer2>地府</answer2>
      <answer3>方寸山</answer3>
      <rightanswer>2</rightanswer>
      <rightrewardid>5840</rightrewardid>
      <errorrewardid>5850</errorrewardid>
    </fire.pb.mission.SActivityQuestion>
  </entry>
  <entry>
    <int>69</int>
    <fire.pb.mission.SActivityQuestion>
      <id>69</id>
      <questionid>69</questionid>
      <step>0</step>
      <question>以下那个门派能给队友加奶?</question>
      <answer1>狮驼岭</answer1>
      <answer2>凌波城</answer2>
      <answer3>普陀山</answer3>
      <rightanswer>3</rightanswer>
      <rightrewardid>5840</rightrewardid>
      <errorrewardid>5850</errorrewardid>
    </fire.pb.mission.SActivityQuestion>
  </entry>
  <entry>
    <int>70</int>
    <fire.pb.mission.SActivityQuestion>
      <id>70</id>
      <questionid>70</questionid>
      <step>0</step>
      <question>以下那个BOSS难度最小？</question>
      <answer1>蚩尤封印</answer1>
      <answer2>6星地煞</answer2>
      <answer3>生死决</answer3>
      <rightanswer>1</rightanswer>
      <rightrewardid>5840</rightrewardid>
      <errorrewardid>5850</errorrewardid>
    </fire.pb.mission.SActivityQuestion>
  </entry>
  <entry>
    <int>71</int>
    <fire.pb.mission.SActivityQuestion>
      <id>71</id>
      <questionid>71</questionid>
      <step>0</step>
      <question>发现BUG应该找谁？</question>
      <answer1>技术负责人</answer1>
      <answer2>GM</answer2>
      <answer3>忽略</answer3>
      <rightanswer>1</rightanswer>
      <rightrewardid>5840</rightrewardid>
      <errorrewardid>5850</errorrewardid>
    </fire.pb.mission.SActivityQuestion>
  </entry>
  <entry>
    <int>72</int>
    <fire.pb.mission.SActivityQuestion>
      <id>72</id>
      <questionid>72</questionid>
      <step>0</step>
      <question>发现BUG应该找谁？</question>
      <answer1>技术负责人</answer1>
      <answer2>GM</answer2>
      <answer3>忽略</answer3>
      <rightanswer>1</rightanswer>
      <rightrewardid>5840</rightrewardid>
      <errorrewardid>5850</errorrewardid>
    </fire.pb.mission.SActivityQuestion>
  </entry>
  <entry>
    <int>73</int>
    <fire.pb.mission.SActivityQuestion>
      <id>73</id>
      <questionid>73</questionid>
      <step>0</step>
      <question>发现BUG应该找谁？</question>
      <answer1>技术负责人</answer1>
      <answer2>GM</answer2>
      <answer3>忽略</answer3>
      <rightanswer>1</rightanswer>
      <rightrewardid>5840</rightrewardid>
      <errorrewardid>5850</errorrewardid>
    </fire.pb.mission.SActivityQuestion>
  </entry>
  <entry>
    <int>74</int>
    <fire.pb.mission.SActivityQuestion>
      <id>74</id>
      <questionid>74</questionid>
      <step>0</step>
      <question>以下那个是技术的QQ？</question>
      <answer1>123456789</answer1>
      <answer2>恭喜发财</answer2>
      <answer3>69783616</answer3>
      <rightanswer>3</rightanswer>
      <rightrewardid>5840</rightrewardid>
      <errorrewardid>5850</errorrewardid>
    </fire.pb.mission.SActivityQuestion>
  </entry>
  <entry>
    <int>75</int>
    <fire.pb.mission.SActivityQuestion>
      <id>75</id>
      <questionid>75</questionid>
      <step>0</step>
      <question>以下那个是技术的QQ？</question>
      <answer1>123456789</answer1>
      <answer2>恭喜发财</answer2>
      <answer3>69783616</answer3>
      <rightanswer>3</rightanswer>
      <rightrewardid>5840</rightrewardid>
      <errorrewardid>5850</errorrewardid>
    </fire.pb.mission.SActivityQuestion>
  </entry>
  <entry>
    <int>76</int>
    <fire.pb.mission.SActivityQuestion>
      <id>76</id>
      <questionid>76</questionid>
      <step>0</step>
      <question>以下那个是技术的QQ？</question>
      <answer1>123456789</answer1>
      <answer2>恭喜发财</answer2>
      <answer3>69783616</answer3>
      <rightanswer>2</rightanswer>
      <rightrewardid>5840</rightrewardid>
      <errorrewardid>5850</errorrewardid>
    </fire.pb.mission.SActivityQuestion>
  </entry>
  <entry>
    <int>77</int>
    <fire.pb.mission.SActivityQuestion>
      <id>77</id>
      <questionid>77</questionid>
      <step>0</step>
      <question>以下那个是技术的QQ？</question>
      <answer1>123456789</answer1>
      <answer2>恭喜发财</answer2>
      <answer3>69783616</answer3>
      <rightanswer>3</rightanswer>
      <rightrewardid>5840</rightrewardid>
      <errorrewardid>5850</errorrewardid>
    </fire.pb.mission.SActivityQuestion>
  </entry>
</tree-map>