<?xml version="1.0" encoding="utf-8" ?>
<tree-map>
  <no-comparator/>
  <entry>
    <int>1</int>
    <fire.pb.npc.SRide>
      <id>1</id>
      <ridemodel>101</ridemodel>
    </fire.pb.npc.SRide>
  </entry>
  <entry>
    <int>2</int>
    <fire.pb.npc.SRide>
      <id>2</id>
      <ridemodel>701</ridemodel>
    </fire.pb.npc.SRide>
  </entry>
  <entry>
    <int>3</int>
    <fire.pb.npc.SRide>
      <id>3</id>
      <ridemodel>301</ridemodel>
    </fire.pb.npc.SRide>
  </entry>
  <entry>
    <int>4</int>
    <fire.pb.npc.SRide>
      <id>4</id>
      <ridemodel>401</ridemodel>
    </fire.pb.npc.SRide>
  </entry>
  <entry>
    <int>5</int>
    <fire.pb.npc.SRide>
      <id>5</id>
      <ridemodel>501</ridemodel>
    </fire.pb.npc.SRide>
  </entry>
  <entry>
    <int>6</int>
    <fire.pb.npc.SRide>
      <id>6</id>
      <ridemodel>601</ridemodel>
    </fire.pb.npc.SRide>
  </entry>
  <entry>
    <int>7</int>
    <fire.pb.npc.SRide>
      <id>7</id>
      <ridemodel>201</ridemodel>
    </fire.pb.npc.SRide>
  </entry>
  <entry>
    <int>8</int>
    <fire.pb.npc.SRide>
      <id>8</id>
      <ridemodel>401</ridemodel>
    </fire.pb.npc.SRide>
  </entry>
  <entry>
    <int>9</int>
    <fire.pb.npc.SRide>
      <id>9</id>
      <ridemodel>601</ridemodel>
    </fire.pb.npc.SRide>
  </entry>
  <entry>
    <int>10</int>
    <fire.pb.npc.SRide>
      <id>10</id>
      <ridemodel>501</ridemodel>
    </fire.pb.npc.SRide>
  </entry>
  <entry>
    <int>11</int>
    <fire.pb.npc.SRide>
      <id>11</id>
      <ridemodel>201</ridemodel>
    </fire.pb.npc.SRide>
  </entry>
  <entry>
    <int>12</int>
    <fire.pb.npc.SRide>
      <id>12</id>
      <ridemodel>701</ridemodel>
    </fire.pb.npc.SRide>
  </entry>
</tree-map>